vg_beat_detectors/__init__.py
vg_beat_detectors/fast_nvg.py
vg_beat_detectors/fast_whvg.py
vg_beat_detectors/vg_detector.py
vg_beat_detectors-0.0.13.dist-info/LICENSE
vg_beat_detectors-0.0.13.dist-info/METADATA
vg_beat_detectors-0.0.13.dist-info/WHEEL
vg_beat_detectors-0.0.13.dist-info/top_level.txt
vg_beat_detectors-0.0.13.dist-info/RECORD
