Metadata-Version: 2.1
Name: vg-beat-detectors
Version: 0.0.13
Summary: Fast and sample-accurate R-peak detectors based on visibility graphs.
Author-email: Jonas Emrich <mail@jonasemrich.de>, Taulant Koka <taulant.koka@tu-darmstadt.de>
Maintainer-email: Jonas Emrich <mail@jonasemrich.de>, Taulant Koka <taulant.koka@tu-darmstadt.de>
License: GNU GENERAL PUBLIC LICENSE
Project-URL: Homepage, https://robustdatascience.org/software/
Project-URL: Source Code, https://github.com/JonasEmrich/vg-beat-detectors
Keywords: cardiovascular,ecg,R-peak,R-peak detector,visibility graphs,beat detector,hrv
Classifier: Programming Language :: Python :: 3
Classifier: License :: OSI Approved :: GNU General Public License v3 (GPLv3)
Classifier: Operating System :: OS Independent
Classifier: Intended Audience :: Science/Research
Requires-Python: >=3.8
License-File: LICENSE
Requires-Dist: numpy
Requires-Dist: scipy
Requires-Dist: ts2vg
Provides-Extra: tests
Requires-Dist: pytest ; extra == 'tests'
Requires-Dist: scipy >=1.10.1 ; extra == 'tests'
Requires-Dist: pooch ; extra == 'tests'
